mkpyp/__init__.py
mkpyp/__main__.py
mkpyp/main.py
mkpyp/templates.py
mkpyp/version.py
mkpyp-0.3.0.dist-info/METADATA
mkpyp-0.3.0.dist-info/WHEEL
mkpyp-0.3.0.dist-info/entry_points.txt
mkpyp-0.3.0.dist-info/licenses/LICENSE
mkpyp-0.3.0.dist-info/RECORD
