Metadata-Version: 2.1
Name: mkpyp
Version: 0.3.0
Summary: make python projects idiomatically
Project-URL: Homepage, https://github.com/liamvdv/mkpyp
Project-URL: Documentation, https://github.com/liamvdv/mkpyp
Project-URL: Source, https://github.com/liamvdv/mkpyp
Project-URL: Changelog, https://github.com/liamvdv/mkpyp
Author-email: Liam van der Viven <liam@vanderviven.com>
License: MIT License
License-File: LICENSE
Classifier: Development Status :: 3 - Alpha
Classifier: Intended Audience :: Developers
Classifier: Programming Language :: Python
Classifier: Programming Language :: Python :: 3
Classifier: Programming Language :: Python :: 3 :: Only
Classifier: Topic :: Internet
Classifier: Topic :: Software Development :: Libraries :: Python Modules
Requires-Python: >=3.9
Requires-Dist: fire==0.5.0
Requires-Dist: inquirerpy==0.3.4
Requires-Dist: pydantic==1.10.4
